lambdaz/__init__.py
lambdaz/aio.py
lambdaz/args.py
lambdaz/base.py
lambdaz/binary.py
lambdaz/call.py
lambdaz/cond.py
lambdaz/consts.py
lambdaz/unary.py
lambdaz/util.py
lambdaz/value.py
lambdaz-0.1.0.dist-info/LICENSE
lambdaz-0.1.0.dist-info/METADATA
lambdaz-0.1.0.dist-info/WHEEL
lambdaz-0.1.0.dist-info/top_level.txt
lambdaz-0.1.0.dist-info/RECORD
